pytis/__init__.py
pytis/bulkcopy.py
pytis/bulkmove.py
pytis/configure.py
pytis/copyright.py
pytis/getip.py
pytis/pytis.py
pytis/toContinue.py
pytis/uniquelist.py
pytis/pylib/__init__.py
pytis/pylib/configobj.py
pytis/pylib/csv.py
pytis/pylib/validate.py
pytis/pylib/util/__init__.py
pytis/pylib/util/date.py
pytis/pylib/util/dicts.py
pytis/pylib/util/func.py
pytis/pylib/util/functional.py
pytis/pylib/util/num.py
pytis/pylib/util/ordereddict.py
pytis/pylib/util/seq.py
pytis/pylib/util/strlib.py
pytis/pylib/util/typelib.py
pytis/pylib3/__init__.py
pytis/pylib3/_version.py
pytis/pylib3/configobj.py
pytis/pylib3/csv.py
pytis/pylib3/validate.py
pytis/pylib3/util/__init__.py
pytis/pylib3/util/date.py
pytis/pylib3/util/dicts.py
pytis/pylib3/util/func.py
pytis/pylib3/util/functional.py
pytis/pylib3/util/num.py
pytis/pylib3/util/ordereddict.py
pytis/pylib3/util/seq.py
pytis/pylib3/util/strlib.py
pytis/pylib3/util/typelib.py
pytis-8.5.0.data/data/pytis/.lvimrc
pytis-8.5.0.data/data/pytis/LICENSE.txt
pytis-8.5.0.data/data/pytis/PyTis_Logo.jpg
pytis-8.5.0.data/data/pytis/README.md
pytis-8.5.0.data/scripts/benchmark
pytis-8.5.0.data/scripts/bulkcopy
pytis-8.5.0.data/scripts/bulkcopy.py
pytis-8.5.0.data/scripts/bulkmove
pytis-8.5.0.data/scripts/bulkmove.py
pytis-8.5.0.data/scripts/clean-pyc
pytis-8.5.0.data/scripts/cleanlogs
pytis-8.5.0.data/scripts/cleanpyc
pytis-8.5.0.data/scripts/cnt
pytis-8.5.0.data/scripts/colorscheme
pytis-8.5.0.data/scripts/configure.py
pytis-8.5.0.data/scripts/copyright
pytis-8.5.0.data/scripts/copyright.py
pytis-8.5.0.data/scripts/csv_split
pytis-8.5.0.data/scripts/docthis
pytis-8.5.0.data/scripts/doscheck
pytis-8.5.0.data/scripts/findrep
pytis-8.5.0.data/scripts/flavorflav
pytis-8.5.0.data/scripts/getip
pytis-8.5.0.data/scripts/getip.py
pytis-8.5.0.data/scripts/lvimrc
pytis-8.5.0.data/scripts/rmfromfile
pytis-8.5.0.data/scripts/to80
pytis-8.5.0.data/scripts/toContinue
pytis-8.5.0.data/scripts/toContinue.py
pytis-8.5.0.data/scripts/uniquelist
pytis-8.5.0.dist-info/METADATA
pytis-8.5.0.dist-info/WHEEL
pytis-8.5.0.dist-info/top_level.txt
pytis-8.5.0.dist-info/RECORD
